cliTextTools/__init__.py
cliTextTools-0.0.11.dist-info/LICENSE
cliTextTools-0.0.11.dist-info/METADATA
cliTextTools-0.0.11.dist-info/WHEEL
cliTextTools-0.0.11.dist-info/top_level.txt
cliTextTools-0.0.11.dist-info/RECORD
