Metadata-Version: 2.1
Name: cliTextTools
Version: 0.0.11
Summary: Text tools for cli based progams
Author: rosejustin601 (Justin Rose)
Author-email: rosejustin601@gmail.com
Keywords: python,cli,texttools
Classifier: Development Status :: 4 - Beta
Classifier: Intended Audience :: Developers
Classifier: Programming Language :: Python :: 3
Classifier: Operating System :: Unix
Classifier: Operating System :: MacOS :: MacOS X
Classifier: Operating System :: Microsoft :: Windows
Classifier: Environment :: Console
Classifier: License :: OSI Approved :: GNU General Public License v3 (GPLv3)
Classifier: Natural Language :: English
License-File: LICENSE
